{
  "schemaVersion": "live-snapshot-automation-status/v1",
  "executionId": "exec-20260716221111109-87f26ed7",
  "lastRunAt": "2026-07-16T22:11:12.947Z",
  "result": "CAPTURED",
  "reason": "SIGNIFICANT_CHANGE",
  "requestedReason": null,
  "round": 19,
  "snapshotId": "live-2026-r19-20260716221111-4f1c74ba",
  "captured": true,
  "skipped": false,
  "auditStatus": "PASS",
  "nextRecommendedCheckAt": "2026-07-17T22:11:11.110Z",
  "marketClosingAt": "2026-07-21T22:29:00.000Z",
  "secondsToClosing": 433068,
  "scheduleWindow": {
    "name": "MORE_THAN_72_HOURS",
    "intervalSeconds": 86400,
    "priority": "LOW"
  },
  "capturePriority": "LOW",
  "changeSummary": {
    "changedPlayers": 7,
    "statusChanges": 4,
    "priceChanges": 0,
    "predictionChanges": 0,
    "idealTeamChanged": false,
    "captainChanged": false,
    "viceChanged": false,
    "matchChanges": 0,
    "closingChanged": false,
    "centralChanged": false
  },
  "previousSnapshotId": "live-2026-r19-20260716200759-7dafaffd",
  "currentFingerprint": "e9a029eb5ea3c98d5b0f6bf988a91575f25948e70205a83e221c4b8370c1a649",
  "previousFingerprint": "397c046b4ac19c545c025c1111bcd6f87f186d311eed95da5aa903b295e756de",
  "staleLockRecovered": false,
  "lockReleased": true,
  "errorCode": null,
  "errorMessage": null,
  "dryRun": false,
  "failureCount": 0,
  "consecutiveFailureCount": 0,
  "lastSuccessfulRunAt": "2026-07-16T22:11:12.947Z",
  "lastFailureAt": null
}
