{
  "schemaVersion": "live-snapshot-automation-status/v1",
  "executionId": "exec-20260719000147726-599b6444",
  "lastRunAt": "2026-07-19T00:01:49.691Z",
  "result": "CAPTURED",
  "reason": "SIGNIFICANT_CHANGE",
  "requestedReason": null,
  "round": 19,
  "snapshotId": "live-2026-r19-20260719000147-40b13fe6",
  "captured": true,
  "skipped": false,
  "auditStatus": "PASS",
  "nextRecommendedCheckAt": "2026-07-19T12:01:47.727Z",
  "marketClosingAt": "2026-07-21T22:29:00.000Z",
  "secondsToClosing": 253632,
  "scheduleWindow": {
    "name": "SEVENTY_TWO_TO_TWENTY_FOUR_HOURS",
    "intervalSeconds": 43200,
    "priority": "MEDIUM"
  },
  "capturePriority": "MEDIUM",
  "changeSummary": {
    "changedPlayers": 3,
    "statusChanges": 2,
    "priceChanges": 0,
    "predictionChanges": 0,
    "idealTeamChanged": false,
    "captainChanged": false,
    "viceChanged": false,
    "matchChanges": 0,
    "closingChanged": false,
    "centralChanged": false
  },
  "previousSnapshotId": "live-2026-r19-20260718191653-dafa3311",
  "currentFingerprint": "b6725465098a0bdb9131d32536d42434ae4ecbf873f87f9d9f59dae3c019ee97",
  "previousFingerprint": "b34dcad8ac0f979c57b21a76d8b1e8ea95b16a7cc68096c66b48c6c8b677c6d8",
  "staleLockRecovered": false,
  "lockReleased": true,
  "errorCode": null,
  "errorMessage": null,
  "dryRun": false,
  "failureCount": 0,
  "consecutiveFailureCount": 0,
  "lastSuccessfulRunAt": "2026-07-19T00:01:49.691Z",
  "lastFailureAt": null
}
