{
  "schemaVersion": "live-snapshot-change-history/v1",
  "season": 2026,
  "round": 19,
  "changes": [
    {
      "previousSnapshotId": "live-2026-r19-20260712120630-b5422fbb",
      "currentSnapshotId": "live-2026-r19-20260712215932-ec31a8f3",
      "capturedAt": "2026-07-12T21:59:32.686Z",
      "changedPlayers": 2,
      "statusChanges": 1,
      "priceChanges": 0,
      "predictionChanges": 0,
      "idealTeamChanged": false,
      "captainChanged": false,
      "viceChanged": false,
      "matchChanges": 0,
      "closingChanged": false,
      "summary": "Mudanca relevante detectada.",
      "executionId": "exec-20260712215932685-a00ecb6b"
    },
    {
      "previousSnapshotId": "live-2026-r19-20260712215932-ec31a8f3",
      "currentSnapshotId": "live-2026-r19-20260713194103-f05ff804",
      "capturedAt": "2026-07-13T19:41:03.976Z",
      "changedPlayers": 3,
      "statusChanges": 1,
      "priceChanges": 0,
      "predictionChanges": 0,
      "idealTeamChanged": false,
      "captainChanged": false,
      "viceChanged": false,
      "matchChanges": 0,
      "closingChanged": false,
      "summary": "Mudanca relevante detectada.",
      "executionId": "exec-20260713194103975-6e06f460"
    },
    {
      "previousSnapshotId": "live-2026-r19-20260713194103-f05ff804",
      "currentSnapshotId": "live-2026-r19-20260714032124-97c52087",
      "capturedAt": "2026-07-14T03:21:24.022Z",
      "changedPlayers": 4,
      "statusChanges": 3,
      "priceChanges": 0,
      "predictionChanges": 0,
      "idealTeamChanged": false,
      "captainChanged": false,
      "viceChanged": false,
      "matchChanges": 0,
      "closingChanged": false,
      "summary": "Mudanca relevante detectada.",
      "executionId": "exec-20260714032124021-551a6697"
    },
    {
      "previousSnapshotId": "live-2026-r19-20260714032124-97c52087",
      "currentSnapshotId": "live-2026-r19-20260714154001-d865fc7d",
      "capturedAt": "2026-07-14T15:40:01.231Z",
      "changedPlayers": 4,
      "statusChanges": 4,
      "priceChanges": 0,
      "predictionChanges": 0,
      "idealTeamChanged": false,
      "captainChanged": false,
      "viceChanged": false,
      "matchChanges": 0,
      "closingChanged": false,
      "summary": "Mudanca relevante detectada.",
      "executionId": "exec-20260714154001230-7a5a4f5c"
    },
    {
      "previousSnapshotId": "live-2026-r19-20260714154001-d865fc7d",
      "currentSnapshotId": "live-2026-r19-20260715140218-52ac10dd",
      "capturedAt": "2026-07-15T14:02:18.096Z",
      "changedPlayers": 4,
      "statusChanges": 1,
      "priceChanges": 0,
      "predictionChanges": 0,
      "idealTeamChanged": false,
      "captainChanged": false,
      "viceChanged": false,
      "matchChanges": 0,
      "closingChanged": false,
      "summary": "Mudanca relevante detectada.",
      "executionId": "exec-20260715140218095-a46ecf9c"
    },
    {
      "previousSnapshotId": "live-2026-r19-20260715140218-52ac10dd",
      "currentSnapshotId": "live-2026-r19-20260715230614-660e744c",
      "capturedAt": "2026-07-15T23:06:14.556Z",
      "changedPlayers": 17,
      "statusChanges": 10,
      "priceChanges": 0,
      "predictionChanges": 0,
      "idealTeamChanged": false,
      "captainChanged": false,
      "viceChanged": false,
      "matchChanges": 0,
      "closingChanged": false,
      "summary": "Mudanca relevante detectada.",
      "executionId": "exec-20260715230614555-22951e23"
    },
    {
      "previousSnapshotId": "live-2026-r19-20260715230614-660e744c",
      "currentSnapshotId": "live-2026-r19-20260716200759-7dafaffd",
      "capturedAt": "2026-07-16T20:07:59.472Z",
      "changedPlayers": 12,
      "statusChanges": 10,
      "priceChanges": 0,
      "predictionChanges": 0,
      "idealTeamChanged": false,
      "captainChanged": false,
      "viceChanged": false,
      "matchChanges": 0,
      "closingChanged": false,
      "summary": "Mudanca relevante detectada.",
      "executionId": "exec-20260716200759472-5f903e6b"
    },
    {
      "previousSnapshotId": "live-2026-r19-20260716200759-7dafaffd",
      "currentSnapshotId": "live-2026-r19-20260716221111-4f1c74ba",
      "capturedAt": "2026-07-16T22:11:11.110Z",
      "changedPlayers": 7,
      "statusChanges": 4,
      "priceChanges": 0,
      "predictionChanges": 0,
      "idealTeamChanged": false,
      "captainChanged": false,
      "viceChanged": false,
      "matchChanges": 0,
      "closingChanged": false,
      "summary": "Mudanca relevante detectada.",
      "executionId": "exec-20260716221111109-87f26ed7"
    },
    {
      "previousSnapshotId": "live-2026-r19-20260716221111-4f1c74ba",
      "currentSnapshotId": "live-2026-r19-20260717000635-bdc0e978",
      "capturedAt": "2026-07-17T00:06:35.083Z",
      "changedPlayers": 13,
      "statusChanges": 11,
      "priceChanges": 0,
      "predictionChanges": 0,
      "idealTeamChanged": false,
      "captainChanged": false,
      "viceChanged": false,
      "matchChanges": 0,
      "closingChanged": false,
      "summary": "Mudanca relevante detectada.",
      "executionId": "exec-20260717000635082-ad0680d8"
    },
    {
      "previousSnapshotId": "live-2026-r19-20260717000635-bdc0e978",
      "currentSnapshotId": "live-2026-r19-20260717171924-79fe034d",
      "capturedAt": "2026-07-17T17:19:24.779Z",
      "changedPlayers": 4,
      "statusChanges": 2,
      "priceChanges": 0,
      "predictionChanges": 0,
      "idealTeamChanged": false,
      "captainChanged": false,
      "viceChanged": false,
      "matchChanges": 0,
      "closingChanged": false,
      "summary": "Mudanca relevante detectada.",
      "executionId": "exec-20260717171924778-b050b80e"
    },
    {
      "previousSnapshotId": "live-2026-r19-20260717171924-79fe034d",
      "currentSnapshotId": "live-2026-r19-20260717225759-cc13cbb3",
      "capturedAt": "2026-07-17T22:57:59.346Z",
      "changedPlayers": 4,
      "statusChanges": 4,
      "priceChanges": 0,
      "predictionChanges": 0,
      "idealTeamChanged": false,
      "captainChanged": false,
      "viceChanged": false,
      "matchChanges": 0,
      "closingChanged": false,
      "summary": "Mudanca relevante detectada.",
      "executionId": "exec-20260717225759345-58412aa8"
    }
  ]
}
